<?xml version='1.0' encoding='utf-8'?>
<Tiles><Tile x="0" y="0" z="0"><Min x="45.0" y="13.0" z="156.0" /><Max x="161.0" y="330.0" z="216.0" /></Tile><Tile x="0" y="0" z="1"><Min x="36.0" y="13.0" z="217.0" /><Max x="161.0" y="330.0" z="324.0" /></Tile><Tile x="1" y="0" z="0"><Min x="162.0" y="8.0" z="148.0" /><Max x="349.0" y="330.0" z="216.0" /></Tile><Tile x="1" y="0" z="1"><Min x="162.0" y="8.0" z="217.0" /><Max x="347.0" y="330.0" z="316.0" /></Tile><Tile x="0" y="1" z="0"><Min x="103.0" y="331.0" z="69.0" /><Max x="234.0" y="653.0" z="194.0" /></Tile><Tile x="0" y="1" z="1"><Min x="89.0" y="331.0" z="195.0" /><Max x="234.0" y="653.0" z="486.0" /></Tile><Tile x="1" y="1" z="0"><Min x="235.0" y="331.0" z="69.0" /><Max x="401.0" y="653.0" z="194.0" /></Tile><Tile x="1" y="1" z="1"><Min x="235.0" y="331.0" z="195.0" /><Max x="400.0" y="653.0" z="313.0" /></Tile><Tile x="0" y="2" z="0"><Min x="107.0" y="654.0" z="101.0" /><Max x="260.0" y="954.0" z="226.0" /></Tile><Tile x="0" y="2" z="1"><Min x="86.0" y="654.0" z="227.0" /><Max x="260.0" y="968.0" z="333.0" /></Tile><Tile x="1" y="2" z="0"><Min x="261.0" y="654.0" z="101.0" /><Max x="402.0" y="972.0" z="226.0" /></Tile><Tile x="1" y="2" z="1"><Min x="261.0" y="654.0" z="227.0" /><Max x="383.0" y="977.0" z="315.0" /></Tile></Tiles>